{
  "supply_point": {
    "verified": true,
    "cups": "ES0031101322018013GN0F",
    "address": "Pedro López 13 BJO-E",
    "status": "active"
  },
  "holder": {
    "vat": "58291270R",
    "vatvalid": true,
    "vatexists": false,
    "privacy_policy_accepted": true,
    "name": "Perico",
    "surname1": "Palote",
    "surname2": "Romero",
    "address": "Percebe 13",
    "postal_code": "17003",
    "state": {
      "id": 1,
      "name": "Araba"
    },
    "city": {
      "id": 7097,
      "name": "Alegría-Dulantzi"
    },
    "email": "perico@gmail.com",
    "email2": "perico@gmail.com",
    "phone1": "672555212",
    "phone2": "555555555",
    "language": {
      "code": "ca_ES",
      "name": "Català"
    },
    "isphisical": true
  },
  "payment": {
    "iban": "ES77 1234 1234 1612 3456 7890",
    "sepa_accepted": true,
    "voluntary_cent": false
  },
  "member": {
    "is_member": false,
    "invite_token" : false,
    "become_member": true
  }
}
